README.md
setup.cfg
setup.py
pegass_auth/__init__.py
pegass_auth/__version__.py
pegass_auth/pegass.py
pegass_auth.egg-info/PKG-INFO
pegass_auth.egg-info/SOURCES.txt
pegass_auth.egg-info/dependency_links.txt
pegass_auth.egg-info/requires.txt
pegass_auth.egg-info/top_level.txt