Metadata-Version: 2.1
Name: pegass-auth
Version: 1.0.0
Summary: pegass_auth is a tiny client tool to help you make some HTTP request on Pegass
Home-page: https://github.com/Annouar/pegass_auth
Author: Annouar
License: MIT
Project-URL: Bug Reports, https://github.com/Annouar/pegass_auth/issues
Keywords: pegass croix rouge login authentication
Platform: UNKNOWN
